[
  {
    "keyword": "Feature",
    "name": "Calculator",
    "line": 1,
    "id": "calculator",
    "tags": [],
    "uri": "Calculator.feature",
    "elements": [
      {
        "id": "calculator;verify-saving-calculator",
        "keyword": "Scenario",
        "line": 7,
        "name": "Verify saving calculator",
        "tags": [],
        "type": "scenario",
        "steps": [
          {
            "arguments": [],
            "keyword": "Given ",
            "line": 4,
            "name": "I m launch web application",
            "result": {
              "status": "passed",
              "duration": 6335000000
            }
          },
          {
            "arguments": [],
            "keyword": "When ",
            "line": 8,
            "name": "I hover on resource tab",
            "result": {
              "status": "passed",
              "duration": 1194000000
            }
          },
          {
            "arguments": [],
            "keyword": "Then ",
            "line": 9,
            "name": "Resources drop-down is open and I click Saving Calculator button",
            "result": {
              "status": "passed",
              "duration": 8972000000
            }
          },
          {
            "arguments": [],
            "keyword": "Then ",
            "line": 10,
            "name": "I click Messaging Api button",
            "result": {
              "status": "passed",
              "duration": 1155000000
            }
          },
          {
            "arguments": [],
            "keyword": "And ",
            "line": 11,
            "name": "I click continue button",
            "result": {
              "status": "passed",
              "duration": 1261000000
            }
          },
          {
            "arguments": [],
            "keyword": "And ",
            "line": 12,
            "name": "I type '1' to the Local Numbers input",
            "result": {
              "status": "passed",
              "duration": 2924000000
            }
          },
          {
            "arguments": [],
            "keyword": "And ",
            "line": 13,
            "name": "I type '1' to the Toll-free Numbers",
            "result": {
              "status": "passed",
              "duration": 1194000000
            }
          },
          {
            "arguments": [],
            "keyword": "Then ",
            "line": 14,
            "name": "I click continue button again",
            "result": {
              "status": "passed",
              "duration": 911000000
            }
          },
          {
            "arguments": [],
            "keyword": "And ",
            "line": 15,
            "name": "I see posible savings",
            "result": {
              "status": "passed",
              "duration": 142000000
            }
          }
        ]
      }
    ]
  }
]